megalamp
