Metadata-Version: 1.0
Name: megalamp-test
Version: 0.19
Summary: Test model of mega lamp
Home-page: https://bitbucket.org/panaetov/megalamp
Author: Panaetov Alexey
Author-email: panaetovaa@gmail.com
License: BSD
Keywords: python tornado
Platform: UNKNOWN
